get_time/__init__.py
get_time-0.0.3.dist-info/METADATA
get_time-0.0.3.dist-info/WHEEL
get_time-0.0.3.dist-info/entry_points.txt
get_time-0.0.3.dist-info/top_level.txt
get_time-0.0.3.dist-info/RECORD
