Metadata-Version: 2.1
Name: get-time
Version: 0.0.3
Summary: 获取任意时间
Home-page: https://github.com/Coxhuang/get_time
Author: 黄民航
Author-email: gmhesat@gmail.com
License: UNKNOWN
Platform: UNKNOWN
